cringelord/__init__.py
cringelord/app/__init__.py
cringelord/app/get_cringe_setting.py
cringelord/app/init_project.py
cringelord/app/setup/__init__.py
cringelord/app/setup/setup_cringelord.py
cringelord/app/setup/toml_parser.py
cringelord/app/setup/exceptions/__init__.py
cringelord/app/setup/exceptions/setup_error.py
cringelord/service/__init__.py
cringelord/service/get_setting_service.py
cringelord/service/setup_service.py
cringelord/service/exceptions/__init__.py
cringelord/service/exceptions/missing_setting.py
cringelord/service/models/__init__.py
cringelord/service/models/cringe_config.py
cringelord/service/models/cringe_environment.py
cringelord/service/models/cringe_mode.py
cringelord/service/models/cringe_toml.py
cringelord/service/models/env_names.py
cringelord/service/models/exceptions/__init__.py
cringelord/service/models/exceptions/missing_config_value.py
cringelord/service/models/exceptions/setting_mismatch.py
cringelord-1.2.0.dist-info/METADATA
cringelord-1.2.0.dist-info/WHEEL
cringelord-1.2.0.dist-info/licenses/LICENSE.txt
cringelord-1.2.0.dist-info/RECORD
